Metadata-Version: 2.1
Name: tableapple
Version: 0.1
Summary: Print and copy greetings based on user input
Author: Your Name
Requires-Dist: pyperclip
